{
  "kind": "spec_vs_diff_report",
  "version": "1.0",
  "generatedAt": "2026-03-01T18:04:33.694Z",
  "summary": "The diff implements a comprehensive visual theme refresh across the frontend matching REQ-20. All major pages (IndexPage, GeneratePage, GalleryPage, CreditsPage, AdminPage) and supporting components have been updated with dark gradient backgrounds, glassmorphism surfaces, amber/emerald/gold accent colors, sharp typography, and neon-glow hover effects. No blue or purple colors are present in the palette. The implementation appears thorough and consistent with the acceptance criteria.",
  "missing_requirements": [],
  "hallucinated_features": [],
  "confidence": 0.92,
  "changed_files": [
    "frontend-file-summaries.txt",
    "frontend/src/components/AccessDeniedScreen.tsx",
    "frontend/src/components/GalleryCard.tsx",
    "frontend/src/components/GenerationTab.tsx",
    "frontend/src/components/Layout.tsx",
    "frontend/src/components/ProfileSetupModal.tsx",
    "frontend/src/components/ReplicateConfigSetup.tsx",
    "frontend/src/components/StripeConfigSetup.tsx",
    "frontend/src/index.css",
    "frontend/src/pages/AdminPage.tsx",
    "frontend/src/pages/CreditsPage.tsx",
    "frontend/src/pages/GalleryPage.tsx",
    "frontend/src/pages/GeneratePage.tsx",
    "frontend/src/pages/IndexPage.tsx",
    "frontend/src/pages/PaymentFailurePage.tsx",
    "frontend/src/pages/PaymentSuccessPage.tsx",
    "frontend/tailwind.config.js",
    "project_state.json"
  ]
}